AUTHOR.txt
CHANGES.txt
COPYRIGHT.txt
LICENSE.txt
README.txt
bootstrap.py
buildout.cfg
setup.py
src/zam/__init__.py
src/zam.api.egg-info/PKG-INFO
src/zam.api.egg-info/SOURCES.txt
src/zam.api.egg-info/dependency_links.txt
src/zam.api.egg-info/namespace_packages.txt
src/zam.api.egg-info/not-zip-safe
src/zam.api.egg-info/requires.txt
src/zam.api.egg-info/top_level.txt
src/zam/api/README.txt
src/zam/api/__init__.py
src/zam/api/app.zcml
src/zam/api/breadcrumb.py
src/zam/api/breadcrumb.zcml
src/zam/api/configure.zcml
src/zam/api/ftesting.zcml
src/zam/api/i18n.py
src/zam/api/interfaces.py
src/zam/api/layer.py
src/zam/api/layer.zcml
src/zam/api/menu.py
src/zam/api/menu.zcml
src/zam/api/menuitem.zcml
src/zam/api/plugin.py
src/zam/api/testing.py
src/zam/api/tests.py
src/zam/api/browser/README.txt
src/zam/api/browser/__init__.py
src/zam/api/browser/configure.zcml
src/zam/api/browser/plugin.py
src/zam/api/browser/plugins.pt
src/zam/api/browser/tests/__init__.py
src/zam/api/browser/tests/ftesting.zcml
src/zam/api/browser/tests/index.pt
src/zam/api/browser/tests/template.pt
src/zam/api/browser/tests/test.pt
src/zam/api/browser/tests/test_skin.py